py_helpers_lib/__init__.py
py_helpers_lib/Model.ipynb
py_helpers_lib-0.1.19.dist-info/METADATA
py_helpers_lib-0.1.19.dist-info/WHEEL
py_helpers_lib-0.1.19.dist-info/RECORD
