Metadata-Version: 2.3
Name: py-helpers-lib
Version: 0.1.19
Summary: Python Helpers Library
Author: Jose_Henrique_V
Requires-Python: >=3.11
Classifier: Programming Language :: Python :: 3
Classifier: Programming Language :: Python :: 3.11
Classifier: Programming Language :: Python :: 3.12
Classifier: Programming Language :: Python :: 3.13
Requires-Dist: joblib
Requires-Dist: numpy
Requires-Dist: pandas
Requires-Dist: scipy
